<?xml version='1.0' encoding='utf-8'?>
<litp:root-deployments-collection xmlns:xsi="http://www.w3.org/2001/XMLSchema-instance" xmlns:litp="http://www.ericsson.com/litp" xsi:schemaLocation="http://www.ericsson.com/litp litp-xml-schema/litp.xsd" id="deployments">
  <litp:deployment id="d1">
    <in_restore_mode>false</in_restore_mode>
    <litp:deployment-clusters-collection id="clusters">
      <litp:cluster id="c1">
        <litp:cluster-configs-collection id="configs"/>
        <litp:cluster-managed_files-collection id="managed_files"/>
        <litp:cluster-nodes-collection id="nodes">
          <litp:node id="n1">
            <hostname>node1<!--note: this property is not updatable--></hostname>
            <is_locked>false<!--note: this property is not updatable--></is_locked>
            <litp:node-configs-collection id="configs"/>
            <litp:node-file_systems-collection id="file_systems"/>
            <litp:node-items-collection id="items"/>
            <litp:node-managed_files-collection id="managed_files"/>
            <litp:node-network_interfaces-collection id="network_interfaces"/>
            <litp:node-routes-collection id="routes"/>
            <litp:node-services-collection id="services"/>
          </litp:node>
        </litp:cluster-nodes-collection>
        <litp:cluster-services-collection id="services"/>
        <litp:cluster-software-collection id="software"/>
      </litp:cluster>
    </litp:deployment-clusters-collection>
  </litp:deployment>
</litp:root-deployments-collection>